FastAiShuzhiXianxingdaishuJiangyiZhongwenbanV2/README.md
FastAiShuzhiXianxingdaishuJiangyiZhongwenbanV2/__init__.py
FastAiShuzhiXianxingdaishuJiangyiZhongwenbanV2/__main__.py
FastAiShuzhiXianxingdaishuJiangyiZhongwenbanV2/file.epub
FastAiShuzhiXianxingdaishuJiangyiZhongwenbanV2/index.html
FastAiShuzhiXianxingdaishuJiangyiZhongwenbanV2/css/__init__.py
FastAiShuzhiXianxingdaishuJiangyiZhongwenbanV2/css/annotations.css
FastAiShuzhiXianxingdaishuJiangyiZhongwenbanV2/css/main.css
FastAiShuzhiXianxingdaishuJiangyiZhongwenbanV2/css/normalize.css
FastAiShuzhiXianxingdaishuJiangyiZhongwenbanV2/css/popup.css
FastAiShuzhiXianxingdaishuJiangyiZhongwenbanV2/font/__init__.py
FastAiShuzhiXianxingdaishuJiangyiZhongwenbanV2/font/fontello.eot
FastAiShuzhiXianxingdaishuJiangyiZhongwenbanV2/font/fontello.svg
FastAiShuzhiXianxingdaishuJiangyiZhongwenbanV2/font/fontello.ttf
FastAiShuzhiXianxingdaishuJiangyiZhongwenbanV2/font/fontello.woff
FastAiShuzhiXianxingdaishuJiangyiZhongwenbanV2/img/__init__.py
FastAiShuzhiXianxingdaishuJiangyiZhongwenbanV2/img/annotator-glyph-sprite.png
FastAiShuzhiXianxingdaishuJiangyiZhongwenbanV2/img/annotator-icon-sprite.png
FastAiShuzhiXianxingdaishuJiangyiZhongwenbanV2/img/apple-touch-icon.png
FastAiShuzhiXianxingdaishuJiangyiZhongwenbanV2/img/cancelfullscreen.png
FastAiShuzhiXianxingdaishuJiangyiZhongwenbanV2/img/close.png
FastAiShuzhiXianxingdaishuJiangyiZhongwenbanV2/img/fullscreen.png
FastAiShuzhiXianxingdaishuJiangyiZhongwenbanV2/img/loader.gif
FastAiShuzhiXianxingdaishuJiangyiZhongwenbanV2/img/menu-icon.png
FastAiShuzhiXianxingdaishuJiangyiZhongwenbanV2/img/save.png
FastAiShuzhiXianxingdaishuJiangyiZhongwenbanV2/img/saved.png
FastAiShuzhiXianxingdaishuJiangyiZhongwenbanV2/img/settings-s.png
FastAiShuzhiXianxingdaishuJiangyiZhongwenbanV2/img/settings.png
FastAiShuzhiXianxingdaishuJiangyiZhongwenbanV2/img/star.png
FastAiShuzhiXianxingdaishuJiangyiZhongwenbanV2/js/__init__.py
FastAiShuzhiXianxingdaishuJiangyiZhongwenbanV2/js/epub.js
fast_ai_shuzhi_xianxingdaishu_jiangyi_zhongwenban_v2-2024.3.3.0.dist-info/METADATA
fast_ai_shuzhi_xianxingdaishu_jiangyi_zhongwenban_v2-2024.3.3.0.dist-info/WHEEL
fast_ai_shuzhi_xianxingdaishu_jiangyi_zhongwenban_v2-2024.3.3.0.dist-info/entry_points.txt
fast_ai_shuzhi_xianxingdaishu_jiangyi_zhongwenban_v2-2024.3.3.0.dist-info/top_level.txt
fast_ai_shuzhi_xianxingdaishu_jiangyi_zhongwenban_v2-2024.3.3.0.dist-info/RECORD
